runtastic.py
runtastic-1.1.0.dist-info/LICENSE
runtastic-1.1.0.dist-info/METADATA
runtastic-1.1.0.dist-info/WHEEL
runtastic-1.1.0.dist-info/entry_points.txt
runtastic-1.1.0.dist-info/top_level.txt
runtastic-1.1.0.dist-info/zip-safe
runtastic-1.1.0.dist-info/RECORD
