Metadata-Version: 2.1
Name: runtastic
Version: 1.1.0
Summary: Download all your Runtastic activities save to gpx
Home-page: https://github.com/yihong0618/Runtastic
Author: yihong0618
Author-email: zouzou0208@gmail.com
License: MIT
Keywords: runtastic running
Classifier: Development Status :: 4 - Beta
Classifier: Environment :: Console
Classifier: Intended Audience :: Developers
Classifier: License :: OSI Approved :: MIT License
Classifier: Operating System :: OS Independent
Classifier: Programming Language :: Python :: 3.6
Classifier: Programming Language :: Python :: 3.7
Classifier: Programming Language :: Python :: 3.8
Classifier: Topic :: Software Development :: Libraries
License-File: LICENSE
Requires-Dist: httpx
Requires-Dist: gpxpy
